datadog_logger/__init__.py
datadog_logger/handler.py
datadog_logger/py.typed
datadog_logger-1.0.2.dist-info/LICENSE
datadog_logger-1.0.2.dist-info/METADATA
datadog_logger-1.0.2.dist-info/WHEEL
datadog_logger-1.0.2.dist-info/RECORD
