Metadata-Version: 2.1
Name: datadog-logger
Version: 1.0.2
Summary: Python logging handler for DataDog events
License: MIT
Author: uStudio Developers
Author-email: dev@ustudio.com
Requires-Python: >=3.9,<4.0
Classifier: License :: OSI Approved :: MIT License
Classifier: Programming Language :: Python :: 3
Classifier: Programming Language :: Python :: 3.9
Classifier: Programming Language :: Python :: 3.10
Classifier: Programming Language :: Python :: 3.11
Classifier: Programming Language :: Python :: 3.12
Requires-Dist: datadog (>=0.45.0)
